[
	{
		"anonymous": false,
		"inputs": [
			{
				"indexed": true,
				"internalType": "address",
				"name": "tokenContract",
				"type": "address"
			},
			{
				"indexed": true,
				"internalType": "address",
				"name": "owner",
				"type": "address"
			},
			{
				"indexed": false,
				"internalType": "string",
				"name": "title",
				"type": "string"
			},
			{
				"indexed": false,
				"internalType": "uint256",
				"name": "valuation",
				"type": "uint256"
			},
			{
				"indexed": false,
				"internalType": "uint256",
				"name": "totalSupply",
				"type": "uint256"
			}
		],
		"name": "PropertyTokenDeployed",
		"type": "event"
	},
	{
		"inputs": [
			{
				"internalType": "string",
				"name": "_title",
				"type": "string"
			},
			{
				"internalType": "string",
				"name": "_description",
				"type": "string"
			},
			{
				"internalType": "uint256",
				"name": "_pricePerToken",
				"type": "uint256"
			},
			{
				"internalType": "uint256",
				"name": "_totalSupply",
				"type": "uint256"
			},
			{
				"internalType": "string",
				"name": "_ipfsHash",
				"type": "string"
			}
		],
		"name": "createAndSetupProperty",
		"outputs": [
			{
				"internalType": "address",
				"name": "",
				"type": "address"
			}
		],
		"stateMutability": "nonpayable",
		"type": "function"
	},
	{
		"inputs": [
			{
				"internalType": "string",
				"name": "_name",
				"type": "string"
			},
			{
				"internalType": "string",
				"name": "_symbol",
				"type": "string"
			},
			{
				"internalType": "string",
				"name": "_title",
				"type": "string"
			},
			{
				"internalType": "string",
				"name": "_description",
				"type": "string"
			},
			{
				"internalType": "uint256",
				"name": "_valuation",
				"type": "uint256"
			},
			{
				"internalType": "uint256",
				"name": "_totalSupply",
				"type": "uint256"
			},
			{
				"internalType": "uint256",
				"name": "_pricePerToken",
				"type": "uint256"
			},
			{
				"internalType": "string",
				"name": "_ipfsHash",
				"type": "string"
			}
		],
		"name": "createPropertyToken",
		"outputs": [
			{
				"internalType": "address",
				"name": "",
				"type": "address"
			}
		],
		"stateMutability": "nonpayable",
		"type": "function"
	},
	{
		"inputs": [
			{
				"internalType": "uint256",
				"name": "",
				"type": "uint256"
			}
		],
		"name": "deployedProperties",
		"outputs": [
			{
				"internalType": "address",
				"name": "",
				"type": "address"
			}
		],
		"stateMutability": "view",
		"type": "function"
	},
	{
		"inputs": [],
		"name": "getDeployedProperties",
		"outputs": [
			{
				"internalType": "address[]",
				"name": "",
				"type": "address[]"
			}
		],
		"stateMutability": "view",
		"type": "function"
	},
	{
		"inputs": [
			{
				"internalType": "address",
				"name": "_owner",
				"type": "address"
			}
		],
		"name": "getOwnerProperties",
		"outputs": [
			{
				"internalType": "address[]",
				"name": "",
				"type": "address[]"
			}
		],
		"stateMutability": "view",
		"type": "function"
	},
	{
		"inputs": [],
		"name": "getTotalProperties",
		"outputs": [
			{
				"internalType": "uint256",
				"name": "",
				"type": "uint256"
			}
		],
		"stateMutability": "view",
		"type": "function"
	},
	{
		"inputs": [
			{
				"internalType": "address",
				"name": "",
				"type": "address"
			}
		],
		"name": "isValidProperty",
		"outputs": [
			{
				"internalType": "bool",
				"name": "",
				"type": "bool"
			}
		],
		"stateMutability": "view",
		"type": "function"
	},
	{
		"inputs": [
			{
				"internalType": "address",
				"name": "",
				"type": "address"
			},
			{
				"internalType": "uint256",
				"name": "",
				"type": "uint256"
			}
		],
		"name": "ownerProperties",
		"outputs": [
			{
				"internalType": "address",
				"name": "",
				"type": "address"
			}
		],
		"stateMutability": "view",
		"type": "function"
	},
	{
		"inputs": [
			{
				"internalType": "address",
				"name": "_propertyAddress",
				"type": "address"
			}
		],
		"name": "validateProperty",
		"outputs": [
			{
				"internalType": "bool",
				"name": "",
				"type": "bool"
			}
		],
		"stateMutability": "view",
		"type": "function"
	}
]